huntflow_webhook_models-0.1.21.dist-info/METADATA
huntflow_webhook_models-0.1.21.dist-info/WHEEL
huntflow_webhook_models-0.1.21.dist-info/entry_points.txt
huntflow_webhook_models-0.1.21.dist-info/licenses/LICENSE
huntflow_webhook_models/__init__.py
huntflow_webhook_models/applicant.py
huntflow_webhook_models/base.py
huntflow_webhook_models/common_models/__init__.py
huntflow_webhook_models/common_models/account_survey.py
huntflow_webhook_models/common_models/applicant.py
huntflow_webhook_models/common_models/applicant_offer.py
huntflow_webhook_models/common_models/calendar_event.py
huntflow_webhook_models/common_models/hf_base.py
huntflow_webhook_models/common_models/recruitment_evaluation.py
huntflow_webhook_models/common_models/response.py
huntflow_webhook_models/common_models/survey_answer.py
huntflow_webhook_models/common_models/survey_questionary.py
huntflow_webhook_models/common_models/vacancy.py
huntflow_webhook_models/common_models/vacancy_request.py
huntflow_webhook_models/consts.py
huntflow_webhook_models/offer.py
huntflow_webhook_models/recruitment_evaluation.py
huntflow_webhook_models/response.py
huntflow_webhook_models/survey_questionary.py
huntflow_webhook_models/vacancy.py
huntflow_webhook_models/vacancy_request.py
huntflow_webhook_models-0.1.21.dist-info/RECORD
