Metadata-Version: 2.1
Name: huntflow-webhook-models
Version: 0.1.21
Summary: Huntflow webhooks requests data models
Author-Email: Developers huntflow <developer@huntflow.ru>
License: MIT
Classifier: Programming Language :: Python :: 3
Classifier: Programming Language :: Python :: 3.8
Classifier: Programming Language :: Python :: 3.9
Classifier: Programming Language :: Python :: 3.10
Classifier: Programming Language :: Python :: 3.11
Requires-Python: >=3.8
Requires-Dist: pydantic>=2.3.0
Requires-Dist: openapi-schema-pydantic>=1.2.4
